{
  "start_time": 1687359600,
  "status": "Cancelada",
  "title": "REUNIÃO CONJUNTA",
  "description": "(REQ 11/2023 CTUR, do deputado Bibo Nunes; REQ 87/2023 CSPCCO, do deputado Coronel Meira)\r\n\r\nConvidados:\r\n\r\n1) Sra. KARLA ANDREA RODRIGUES DOS SANTOS, Coordenadora-Geral do Departamento de Investimentos da Secretaria Nacional de Aviação Civil do Ministério de Portos e Aeroportos (confirmada);\r\n\r\n2)  Sr. GIOVANO PALMA - Superintendente de Infraestrutura Aeroportuária da Agência Nacional de Aviação Civil - ANAC (confirmado);\r\n\r\n3) Sr. CAIO BORTONE RAMOS RIBEIRO, Delegado da Polícia Federal, Chefe da Divisão de Controle de Migração e Segurança Aeroportuária da Polícia Federal (confirmado);\r\n\r\n4) Sr. RUY AMPARO, Diretor de Segurança e Operações de Voo da Associação Brasileira das Empresas Aéreas, representando a Latam Airlines Brasil (confirmado);\r\n\r\n5) Sr. MICHEL GOMES - Repórter no G1 Goiás (confirmado);\r\n\r\n6) Sr. MOZART FÉLIX - Diretor da Associação dos Delegados de Polícia do Brasil - ADEPOL (confirmado);\r\n\r\n7) Representante da GRU Airport; e,\r\n\r\n8) Representante do Ministério das Relações Exteriores.",
  "type": "Audiência Pública",
  "location_name": "Anexo II, Plenário 05",
  "document_url": "https://www.camara.leg.br/internet/ordemdodia/mostrarIntegra.asp?CodTeor=2285435",
  "updated_at": 1709547770
}