{
  "id": 68851,
  "start_time": 1690990369,
  "end_time": 1690991675,
  "status": "Encerrada (Final)",
  "title": "COMISSÃO DE COMUNICAÇÃO",
  "description": "Discussão e votação de propostas legislativas",
  "type": "Reunião Deliberativa",
  "location_name": "Anexo II, Plenário 12",
  "document_url": "https://www.camara.leg.br/internet/ordemdodia/mostrarIntegra.asp?CodTeor=2298105",
  "speeches": [
    {
      "start_time": 1690990364,
      "duration": 413,
      "transcription": "Boa tarde a todos, havendo número regimental declaro aberta a décima segunda reunião extraordinária da comissão de comunicação. Pedi desculpas aos colegas do contratempo, porque a comissão de ética estava ocupando o Plenário Onze, Graças até ao à informação da nossa vicepresidente, Simone Marquito, de que o Plenário doze Estava desocupado, nosso supervisão conseguiu para que a gente pudesse fazer a nossa reunião. Em apreciação, as atas da décima primeira reunião deliberativa realizada No dia catorze de junho, segunda reunião da subcomissão especial sobre o combate à censura também realizada no dia catorze de junho. Informo que a leitura das atos está dispensada nos termos do parágrafo único do artigo quinto do ato da mesa cento e vinte e Três de dois mil e vinte, em votação às atas, aqueles que aprovam permaneçam como se encontram, aprovado. Expediente, informo ao plenário que a relação completa do expediente encontrase publicada na página Da comissão, por esse motivo deixo de ler o expediente. Antes de entrar na ordem do dia, eu gostaria de Falar com os colegas e todos os presentes, uma pequena palavra desse início dos nossos trabalhos nesse segundo semestre. Senhoras e senhoras deputados, servidores, aqueles que nos acompanham nos canais desta casa, mais uma vez boa tarde a todos. Nesse dia que reabrimos os trabalhos da comissão de comunicação Câmara federal é com imensa honra e responsabilidade que me dirijo a todos vocês. É momento para refletirmos sobre a importância da comunicação Em nossa sociedade, e o papel determinante desta comissão no aprimoramento das políticas e regulamentações que governam esse setor. Primeiramente, gostaria de saudar todos os membros da comissão, por seu incansável trabalho em prol da melhoria da comunicação em nosso país. Também agradeço a confiança depositada em nós para presidir esse colegiado, e me comprometo, mais uma vez, A exercer esse cargo com retidão, imparcialidade, dedicação em prol dos interesses da nossa nação. É inegável Vivemos em uma era dominada pela informação e pela tecnologia. A cada dia, novas formas de comunicação surgem, transformando nossa maneira de interagir e compartilhar conhecimento. Essas mudanças impactam diretamente a vida de cada cidadão, e é nosso dever, Como representantes do povo, garantir que a comunicação seja democrática, inclusiva e transparente. Ao longo desse segundo semestre de dois mil e vinte e três, Enfrentaremos diversos desafios, deles é a garantia da liberdade de expressão, pilar essencial para o pleno funcionamento da nossa democracia. É nossa missão garantir que todos os cidadãos tenham a liberdade necessária para se expressar, mas também Assegurar que notícias falsas e desinformação não contaminem o nosso debate público. Além disso, precisamos avançar na pela democratização do acesso à informação e à tecnologia. A comunicação não pode ser privilégio de poucos, ela deve ser direito de todos. É inadmissível que ainda existam regiões no país desconectadas, sem acesso à internet e às informações necessárias para uma vida digna e próspera. Nossa comissão deve empenharse em promover a inclusão digital para que todos os brasileiros possam participar plenamente da sociedade do conhecimento. Temos pela frente árduo trabalho, mas tenho convicção de que com o empenho de todos os membros desta comissão, Conseguiremos avançar em nossos objetivos, e eu conto com a colaboração de cada dos colegas deputados, dos representantes da sociedade civil, Também das instituições e especialistas do setor para que juntos possamos contribuir uma, construir, melhor dizendo, Uma legislação moderna, justa, equitativa para que a comunicação do nosso país cresça cada vez mais. Que esse segundo semestre seja período de intensa produtividade, de diálogo respeitoso, e de busca constante por soluções inovadoras. A comissão de comunicação tem papel fundamental na construção de uma sociedade mais informada, conectada e consciente. Agradeço a todos a atenção, colócome à disposição para ouvir sugestões e ideias que possam contribuir para o trabalho desta comissão. Obrigado a todos e uma excelente jornada de trabalho a todos nós nesse segundo semestre na nossa comissão de comunicação. Também quero aproveitar o ensejo pra falar da excelente ideia da deputada Amália, que nos passou ao chegar aqui pra acho que a gente possa ter acessibilidade nas nossas comissões com intérprete de libras, vou levar Esse pedido pra que a gente possa ter também esse serviço pra que a gente possa incluir ainda mais o povo brasileiro nas nossas discussões. E também quero dizer aos colegas que eu retirei alguns requerimentos de pauta, Requerimentos polêmicos pra que a gente pudesse ter trabalho pouco mais ágil em algumas sessões, me comprometendo Que na próxima sessão a gente possa ter esses requerimentos para debate e apreciação dos colegas. Encontrase na mesa requerimento Diversão de pauta para o item quarenta e dois, TVR dois mil e vinte e três, de iniciativa do deputado Alex Santana, e para o item seis, PLP Duzentos e dezoito dois mil e vinte de iniciativa do deputado Maurício Marcon. Como eles não se fazem presente, eu quero fazer questionamento se algum dos colegas pode subscrever. Subscreva, presidente. Deputada Simone Marteto subscreve os requerimentos de inversão de pauta. Em votação os requerimentos de inversão de pauta, os deputados, 000 os deputados que aprovam permaneçam como se encontram? Quero aproveitar o 0 ensejo pra que já que a gente está, A gente só pediu o item quarenta e dois, que é o TVR dois mil e vinte e três, que a gente possa apreciar também em bloco os TVRs, Seria muito mais profícuo para o nosso trabalho hoje. Então, mais uma vez, em votação os requerimentos de diversão de pauta, os deputados que aprovam permaneçam como se encontram, aprovados os que a promo permaneçam como se encontram, aprovados os requerimentos. Bom presidente. Convido a deputada Amália Barros, pra assumir os trabalhos, já que nos termos do artigo",
      "summary": "Na reunião, o deputado:",
      "speaker": {
        "id": 204356,
        "name": "Amaro Neto",
        "position": "Deputado"
      }
    },
    {
      "start_time": 1690990777,
      "duration": 65,
      "transcription": "Regimento interno da casa, em alguns desses TVRs tem também a nossa relatoria. Obrigada. Pra começar, fazer",
      "summary": "Novo regulamento interno, incluirá relatórios da TVR. Grato. Iniciando.",
      "speaker": {
        "name": "Troca da mesa -- Presidente -- Amaro Neto -- por Participante -- Amália Barros",
        "position": ""
      }
    },
    {
      "start_time": 1690990842,
      "duration": 159,
      "transcription": "Descrição, sou uma pessoa de pele clara, cabelo castanho, pouco abaixo dos ombros, dos meus olhos é uma prótese ocular, eu me encontro agora com vestido verde, uma bota preta e o meu sinal em libras é a mão esquerda na frente de dos olhos, peço a todas as pessoas dessa casa assim como se solicitei a presença de intérprete de libras nessa comissão em todas as comissões, é que sempre que estivermos em público a gente faça a nossa audiodescrição pra inclusão das pessoas com deficiência, principalmente com a deficiência visual. Pra começar então vamos às proposições sujeitas à à apreciação conclusiva pelas pelas comissões, começamos aqui? Serviço de radiodifusão, passase apreciação em bloco dos atos de iothoga e de renovação de iothoga de serviços de radiodifusão sonora e de sons e imagens, item sete a quarenta e oito da pauta, DVRs número dez de dois mil e vinte, vinte e quatro de dois mil e vinte, cento e vinte de dois mil e vinte, duzentos e sete de dois mil e vinte, duzentos e vinte, duzentos quatrocentos e oito de dois mil e vinte, passamos então agora dois mil e vinte e oitenta de dois mil e vinte e noventa e quatro de vinte e cento trezentos e quarenta e dois, quatrocentos e dois, quatrocentos e noventa, todos de dois mil e vinte e passamos a passamos agora dois mil e vinte e dois nove de vinte e dois, doze de vinte e dois, vinte e quarenta e quatro, quarenta e sete, cinquenta, cinquenta e quatro, cinquenta e cinco, oitenta e cento e sete, cento e quarenta e oito, cento e quarenta e nove, duzentos e quarenta, duzentos e quarenta e três, duzentos e cinquenta e quatro, de dois mil e vinte e dois, passamos a passamos a dois mil e vinte e três, de vinte e três, dois de vinte e três, três de dois mil e vinte e três, quatro cinco seis e sete Agora, em discussão os itens do bloco itens sete a quarenta e oito da pauta. Alguém? Não havendo mais quem queira discutir declaro encerrada a discussão, em votação, os senhores deputados",
      "summary": "Deputada propõe inclusão de pessoas com deficiência, principalmente visual, por meio de audiodescrição em público. ela também pede a aprovação em bloco de atos de iothoga e renovação de iothoga de serviços de radiodifusão sonora e de sons e imagens. A discussão sobre os itens relacionados foi encerrada para votação.",
      "speaker": {
        "id": 220596,
        "name": "Amália Barros",
        "position": "Deputada"
      }
    },
    {
      "start_time": 1690991001,
      "duration": 44,
      "transcription": "Nosso presidente. Muito bem obrigado",
      "speaker": {
        "name": "Troca da mesa -- Presidente -- Amália Barros -- por Participante -- Amaro Neto",
        "position": ""
      }
    },
    {
      "start_time": 1690991045,
      "duration": 59,
      "transcription": "Amália, pela condução dos trabalhos. Item seis da pauta, projeto de lei complementar duzentos e dezoito barra dois mil e vinte, do deputado Danilo Forte, que institui a contribuição social para serviços digitais, incidentes sobre a receita bruta de serviços digitais prestados pelas grandes empresas de tecnologia, destinado ao financiamento de programas de renda básica, a pensado PLP dois quatro dois mil e vinte. Requerimento de retirada de pauta com o requerimento de votação nominal de autoria dos deputados Carol da Tora, Gilmar Tato, Camila Jara, Carlos Veras, Rubens Pereira Júnior, Juliana Cardoso, Velter e Denise Pessoa. Nenhum deles se encontra. Então vamos à apreciação do relator deputado Maurício Marcon, que vai ler o seu parecer com a palavra o deputado Maurício Marcon.",
      "summary": "Deputado propõe projeto de lei complementar para cobrar contribuição social de empresas de tecnologia, financiando programas de renda básica. Requerimento de retirada de pauta com votação nominal feito por outros deputados, mas nenhum deles está presente. Relator deputado Maurício Marcon lerá seu parecer.",
      "speaker": {
        "id": 204356,
        "name": "Amaro Neto",
        "position": "Deputado"
      }
    },
    {
      "start_time": 1690991104,
      "duration": 193,
      "transcription": "Obrigado presidente, posso ir direto ao voto? O projeto de lei complementar número duzentos e dezoito de dois mil e vinte propõe a criação da Contribuição sobre serviços digitais tributando às grandes empresas de tecnologia e destinando os recursos arrecadados para programas de renda básica. A contribuição incidirá sobre empresas com receita bruta global superior a quatro ponto cinco bilhões no ano calendário anterior e terá uma alíquota de três por cento sobre a receita bruta. Já o apenso, projeto de lei complementar número dois quatro de dois mil e vinte, tem finalidade semelhante, mas abrange uma quantidade de empresas bem maior, já que o faturamento mínimo para incidência do novo tributo é de cem milhões, ou seja, valor quarenta e cinco vezes menor que o proposto no texto principal. Além disso, pelo texto do Apenso os fatos geradores seriam também mais amplos, como streaming ou download, de conteúdos digitais, como livros, vídeos, músicas, imagens, jogos, aplicativos e softwares online, bem como sua atualizações, Societtivos eletrônicos que permitam a realização de transações econômica ou a transferência de quaisquer conteúdos digitais entre usuários, e apostas comercializadas via canais eletrônicos como internet e telefonia móvel, dispositivos computacionais móveis ou qualquer outro Social digital de comunicação. Em que pese a nova intenção do autor dos projetos financiar programas sociais, é importante analisar as possíveis consequências negativas da implementação das tributações propostas. As contribuições irão reduzir a concorrência no setor de tecnologia, tendo em vista que a tributação adicional proposta pelos projetos pode criar barreiras à entrada de novas empresas no mercado, fortalecendo a posição dominante das grandes empresas de tecnologia. Além disso, em mercado concentrado, o aumento de tributação será pago pelos consumidores, tendo em vista que essas empresas repassarão aumento de custos via aumento do preço dos serviços digitais, prejudicando os consumidores e desestimulando o uso dessas plataformas. Ademais, a tributação adicional pode reduzir os investimentos em pesquisa e desenvolvimento, desestimulando a inovação e a criação de novos produtos e serviços no setor. É importante ressaltar que os novos tributos previstos impactarão o setor como todo, afetando não apenas as grandes empresas de tecnologia, mas também pequenas e médias empresas que atuem no setor, gerando efeito cascata negativo. E por fim, esse novo imposto desencorajará a presença de empresas no Brasil, podendo levar a empresa de tecnologia a reconsiderar sua presença no Brasil, prejudicando a criação de empregos e investimentos no país, reduzindo a competitividade do país. Diante do exposto, o voto é pela rejeição do projeto de lei complementar número duzentos e dezoito de dois mil e vinte pela rejeição do APENS projeto de lei complementar número dois quatro de dois mil e vinte deputado Maurício Marcon relator era isso senhor presidente.",
      "summary": "Deputado propõe rejeição de novos impostos sobre serviços digitais de grandes tecnologia, arguindo possíveis efeitos negativos, como redução de concorrência, aumento de preços, e impacto negativo em empresas pequenas e médias. Sugerem-se alíquotas de 3% para empresas com faturamento acima de R$ 4,5 bilhões e R$ 100 milhões no ano anterior, abrangendo streaming, download de conteúdos digitais, transações online, e apostas comercializadas via canais eletrônicos.",
      "speaker": {
        "id": 220550,
        "name": "Mauricio Marcon",
        "position": "Deputado"
      }
    },
    {
      "start_time": 1690991297,
      "duration": 73,
      "transcription": "O parecer do relator, não havendo quem queira discutir, encerro a discussão, em votação parecer, aqueles que aprovam permaneçam como se encontram, aprovado. Deputado Maurício Marcon quer falar, quer ter o uso da palavra? Podemos seguir? Então está bom deputado, obrigado, obrigado pela pela sua relatoria. Vamos aos itens da ordem do dia, item requerimento trinta e quatro de dois mil e vinte e três, do deputado Jadiel Alencar, que requer realização de audiência pública sobre jornalismo digital e o seu papel no acesso à informação. O deputado não se encontra, alguém deseja subscrever? Do deputado Jadiel Alencar, trinta e quatro dois mil e vinte Subs Estevão presidente. A deputada Simone Marquito subscreve, em votação requerimento. Quer encaminhar, deputado? Não. Aqueles que aprovam permaneçam como se encontram, aprovado. Convido a deputada Simone Marquito para assumir a condução dos trabalhos nos termos",
      "summary": "Deputado encerra discussão e vota parecer favorável ao requerimento 34/2023 de audiência sobre jornalismo digital, deputada Simone Marquito subscreve e assume condução dos trabalhos.",
      "speaker": {
        "id": 204356,
        "name": "Amaro Neto",
        "position": "Deputado"
      }
    },
    {
      "start_time": 1690991370,
      "duration": 20,
      "transcription": "Quarenta e três do regimento interno da casa, próximo requerimento é de nossa autoria.",
      "speaker": {
        "name": "Troca da mesa -- Presidente -- Amaro Neto -- por Participante -- Simone Marquetto",
        "position": ""
      }
    },
    {
      "start_time": 1690991390,
      "duration": 16,
      "transcription": "Por trinta e seis dois mil e vinte e três. Senhor Amaro Neto que requer a realização de evento interno para recepção de autoridades. Concedo a palavra ao autor deputado Amaro Neto pra defender o seu requerimento. Obrigado presidente. É apenas pra que a gente possa",
      "summary": "Deputada pede realização de evento interno para recepção de autoridades, concedendo palavra ao deputado Amaro Neto para defender requerimento.",
      "speaker": {
        "id": 220651,
        "name": "Simone Marquetto",
        "position": "Deputada"
      }
    },
    {
      "start_time": 1690991406,
      "duration": 19,
      "transcription": "Ter a condição de na nossa comissão poder receber as autoridades que porventura venham a participar de eventos aqui da nossa comissão como audiências públicas. Portanto, eu faço pedido aos colegas pela aprovação do nosso requerimento.",
      "summary": "Pedido do Deputado para autoridades poderem participar como audiências públicas em sua comissão.",
      "speaker": {
        "id": 204356,
        "name": "Amaro Neto",
        "position": "Deputado"
      }
    },
    {
      "start_time": 1690991425,
      "duration": 18,
      "transcription": "Deputado com em votação o requerimento. Ninguém se manifesta, vamos pra votação do requerimento. Aqueles que aprovam permaneçam como estão aprovado. Agora eu devolvo a condução dos nossos",
      "summary": "Deputada propõe votação de requerimento; ninguém se manifesta, então vai para votação. Aquele que aprovar manterá voto a favor, deputada devolve condução da sessão.",
      "speaker": {
        "id": 220651,
        "name": "Simone Marquetto",
        "position": "Deputada"
      }
    },
    {
      "start_time": 1690991443,
      "duration": 12,
      "transcription": "Ao deputado Amaro Neto nosso presidente. Obrigado deputado Simone.",
      "speaker": {
        "name": "Troca da mesa -- Presidente -- Simone Marquetto -- por Participante -- Amaro Neto",
        "position": ""
      }
    },
    {
      "start_time": 1690991455,
      "duration": 70,
      "transcription": "Pela condução nos trabalhos, Item três, requerimento quarenta de dois mil e vinte e três, do deputado David Soares, que requer que seja realizada audiência pública na subcomissão especial de comissão da comunicação para debater a atualização das competências da Agência Nacional de Telecomunicações da Anatel. Deputado Maurício Marcos subscreva presidente. Quer a palavra pra poder falar do requerimento, ok, em votação o requerimento, aqueles que aprovam permaneçam como se encontram, aprovado. Vamos às prioridades aos projetos, item quatro, projeto de lei cinco mil trezentos e quarenta e sete barra de dois mil e vinte, do deputado Roberto Lucena, de Lucena, que cria a lei de enfrentamento à desinformação nas eleições, apensado ao PL cinquenta e cinco meia sete de dois mil e vinte. A relatora é a deputada Simone Marquito, parecer pela aprovação deste com o substitutivo e pela rejeição do PL cinco cinco meia sete de dois mil e vinte a pensado. Concedo a palavra relatora à deputada Simone Marquito pra proferir o seu parecer. Com a palavra. Presidente, eu peço",
      "summary": "Deputado pede audiência pública para atualizar competências da Anatel; Aprovação de requerimento para debater lei contra desinformação nas eleições; Deputada Simone Marquito é relatora do projeto e propõe aprovação com substitutivo, rejeição de outro projeto relacionado.",
      "speaker": {
        "id": 204356,
        "name": "Amaro Neto",
        "position": "Deputado"
      }
    },
    {
      "start_time": 1690991525,
      "duration": 64,
      "transcription": "Direto ao voto e fazer resumo da leitura? Bom, esse é projeto muito simples, nós já temos isso em rádios, em televisões e comunicações, é o projeto que traz o megafone, que na verdade coloca os tribunais eleitorais, que coloque no timeline das plataformas digitais a informação sobre o período eleitoral, somente no período eleitoral plataformas digitais e mensagens relevantes acerca da organização do pleito eleitoral e também da segurança de medidas de segurança sanitária dos pleitos no Brasil. É muito simples, então por todo exposto a gente rejeita aquilo que colocava como controle de conteúdo, tudo isso a gente rejeita e aprova então o projeto de lei cinco mil trezentos e quarenta e sete dois mil e vinte na do substitutivo pela rejeição do projeto cinco mil quinhentos e sessenta e sete dois mil e vinte.",
      "summary": "Deputada propôs projeto de lei para publicar informações sobre período eleitoral e medidas sanitárias em plataformas digitais, rejeitando controle de conteúdo. Aprovado substitutivo ao projeto 5567/22.",
      "speaker": {
        "id": 220651,
        "name": "Simone Marquetto",
        "position": "Deputada"
      }
    },
    {
      "start_time": 1690991589,
      "duration": 17,
      "transcription": "Rei discussão parecer da relatora, não havendo quem queira discutir declaro encerrada a discussão, em votação parecer, aqueles que aprovam permaneçam como se encontram, aprovado. Relatora, gostaria ainda de ter uso da palavra? Tranquilo",
      "summary": "Deputado encerra discussão e aprova parecer da relatora, permite-lhe novamente falar.",
      "speaker": {
        "id": 204356,
        "name": "Amaro Neto",
        "position": "Deputado"
      }
    },
    {
      "start_time": 1690991606,
      "duration": 12,
      "transcription": "Pessoal, acho que avanço a gente tem que sempre lembrar que nós temos o direito de informação, o direito de expressão, e responsabilidade também principalmente no período eleitoral, obrigado. Item",
      "summary": "Deputada destaca importância de direito à informação, expressão e responsabilidade, especialmente during período eleitoral.",
      "speaker": {
        "id": 220651,
        "name": "Simone Marquetto",
        "position": "Deputada"
      }
    },
    {
      "start_time": 1690991618,
      "duration": 57,
      "transcription": "Cinco da pauta projeto de lei vinte setenta e seis de dois mil e vinte e dois do Senado Federal, do Senador Eduardo Gomes, que institui o Dia Nacional de Proteção de Dados, relator, deputado Fred Linhares. Não se encontrando o relator, retiro de ofício. Nada mais havendo a tratar, declaro encerrado os trabalhos e convoco reunião extraordinária deliberativa tive a ser realizada dia nove de agosto, quartafeira, às quatorze horas, no plenário onze, com pauta a ser divulgada. Está encerrada a reunião, obrigado a todos.",
      "summary": "Deputado anuncia retirada de seu relatorado no projeto de lei 2076/22 do Senado Federal, que institui o Dia Nacional de Proteção de Dados, e convoca reunião extraordinária deliberativa para o dia 9 de agosto. Reunião então encerrada.",
      "speaker": {
        "id": 204356,
        "name": "Amaro Neto",
        "position": "Deputado"
      }
    }
  ],
  "updated_at": 1709547770
}