{
  "start_time": 1715040000,
  "end_time": 1715083560,
  "title": "COMISSÃO DE EDUCAÇÃO",
  "description": "07/05/2024 - Esportes adaptados para redução da evasão escolar de PCDs e autistas",
  "speeches": [
    {
      "start_time": 1715078416,
      "duration": 353,
      "transcription": "Declaro aberta a presente reunião de audiência pública da Comissão de Educação, convocada com o objetivo de debater a importância dos esportes adaptados como relevante ferramenta na educação da evasão escolar dos PCDs e crianças com autismo. Essa audiência pública está sendo realizada em virtude da aprovação do requerimento de nossa autoria de número trinta e nove de dois mil e vinte e quatro. Os procedimentos a serem adotados na condução dos trabalhos serão os seguintes, cada palestrante terá dez minutos para fazer sua exposição, não sendo permitido a partes. Encerradas as apresentações será concedida a palavra aos parlamentares inscritos por três minutos, Os parlamentares disporão do mesmo tempo para resposta caso haja necessidade. Ao final do debate cada convidado terá três minutos para as suas considerações finais. Informo que esta reunião está sendo transmitida ao vivo pela internet e que pode ser acessada pela página da comissão do portal da câmara ou pelo YouTube no canal oficial da Câmara dos Deputados federais. Após a audiência, as apresentações serão disponibilizadas para consulta na página da comissão. Gostaríamos de registrar a participação dos convidados que participarão virtualmente dessa sessão pública aos quais faço especial agradecimento que são os senhores professor José Ricardo Dávila, mestre em educação física, professor George Francisco de Lima Teles, profissional de Educação Física, mestre em CAFE e conselheiro do Conselho Regional de Educação Física da Primeira Região, o CREF também do doutor Renato de Paula, fisioterapeuta e mestre PhD em bioquímica médica pela Universidade Federal do Rio de Janeiro, PhD em Neurocirência pelo Imperial College em Londres. E o senhor Claudiodo Francisco da Silva Correia, nosso querido Clodoaldo atleta paraolímpico e orgulho nacional dos esportes no Brasil. Clodoaldo hoje é consultor em acessibilidade e inclusão e colunista do portal Uol. Na condição de autor do requerimento gostaria de tecer algumas rápidas considerações. O acesso à educação e o direito à aprendizagem são garantias constitucionais universais, ou seja, estão previstas a todos os brasileiros como dever do estado e da família. A diversidade de experiências, habilidades, contextos e capacidade entre estudantes é uma realidade que deve ser celebrada através da prática educacional inclusiva. Nas últimas décadas, a insistência em modelos pedagógicos padronizados já demonstrou ser pouco eficiente de modo que o presente e o futuro da educação consistem na promoção da diversidade como valor inegociável. Quanto mais respeitadas em suas diferenças, mais os estudantes e educadores avançam, sejam eles pessoas com ou sem deficiência. O esporte conjugado com as práticas escolares é capaz de promover o fortalecimento da autoestima e da sociabilidade, permitindo uma maior interação de alunos com os seus colegas e mantendo interesse pela continuidade nos estudos. Passamos ao uso da palavra pelos nossos convidados por até dez minutos, Quero relembrar que esta audiência pública tem como tema a importância dos esportes adaptados como ferramenta na redução da evasão escolar dos PCDs e crianças com autismo. Passo a palavra para o primeiro palestrante desta audiência pública, o professor José Ricardo Dávila, que diz porá do tempo de dez minutos. Professor, é uma honra para esta comissão têlo conosco, o senhor terá a palavra a partir de agora. Lamentavelmente caiu o link do nosso professor José Ricardo, vamos então avançando com o Professor George Francisco de Lima Teles, eu creio que está conosco, ok? Professor George, também da mesma forma temos a alegria de têlo conosco, honrando esta nossa audiência pública. Professor George, vossa senhoria dispõe do tempo de dez minutos a partir de agora para a sua exposição.",
      "summary": " Deputado inicia audiência pública sobre valor de esportes adaptados em educação, com foco em diminuir evasão escolar de pessoas com deficiência ou autismo. Palestrantes incluem profissionais de educação física, fisioterapeuta e atleta paralímpico. Reunião transmitida ao vivo, apresentações disponibilizadas posteriormente. Breve declaração do deputado sobre educação inclusiva e promoção de diversidade e inclusão.",
      "speaker": {
        "id": 204441,
        "name": "Otoni de Paula",
        "position": "Deputado"
      }
    },
    {
      "start_time": 1715078769,
      "duration": 549,
      "transcription": "Bom bom dia a todos e a todas. Queria iniciar a minha fala cumprimentando o deputado Otônio de Paula, e parabenizando por essa pauta, estendendo o meu cumprimento a todos os presentes, na Comissão de Educação, e cumprimentando aos outros convidados que terão a palavra após a minha exposição. Bom, como representante do Conselho Regional de Educação Física da Primeira Região, eu preciso enaltecer e parabenizar a essa comissão por ter levantado essa discussão e ter oportunizado que pudéssemos debater sobre a educação física como ferramenta fundamental de inserção, inclusão, equidade e prática escolar. Quando a gente pensa numa educação de excelência, a gente não tem que perceber a educação física à parte, quando a oportunidade de potencializar o plano motor, a execução cognitiva, as suas funções executivas, quando a gente consegue ter entendimento onde, quão mais potencializado é a evolução e a maturação dessa criança, mais ele possui desenvolvimento intelectual amplo, e isso reverbera em todas as outras disciplinas, e principalmente isso fortalece a formação do indivíduo. Então deputado federal Antônio de Paula, parabéns por essa pauta. Quando a gente pensa em esportes adaptados, eu acho que foi muito muito coeso a terminologia pra que a gente não falasse sobre esportes paralímpicos que requer toda uma adaptação de regramentos pra os esportes paralímpicos, quando a gente fala de esportes adaptados sim, a gente oportuniza com que através da ludicidade, através do estímulo motor, através do estímulo cognitivo e sensorial que pessoas com deficiência, crianças com deficiência, crianças com autismo, possam sim utilizarse dessa potente ferramenta, que é a educação física, pra que a gente possa propiciar espaço acolhedor, espaço coletivo, espaço inclusivo e espaço equânime. E me permita a gentileza de colocar de não pensarmos apenas nos esportes adaptados. Quando a gente pensa na educação física escolar, principalmente quando a gente pensa na educação física escolar em turmas que possuam crianças com deficiência, a gente potencializa uma transformação social. A gente propicia que crianças neurotípicas tenham esse convívio, tenham essa interação, e principalmente quando a gente fala da educação física num espaço mais amplo, num espaço mais coletivo, num espaço mais inclusivo, a gente não só propicia. Acesso a pessoas e crianças com deficiência, quando a gente propicia a quebra de preconceitos por crianças neurotípicas. Então deputado federal Antônio de Paulo e a todos os colegas que nos disputam. É quase que, óbvio quando a gente pensa na educação física como uma potente ferramenta de combate à evasão escolar, e a gente pode estender a outros nichos da sociedade onde a educação física ela é capaz de corroborar com essa essa educação mais presente essa transformação da sociedade, e pensando nisso deputado federal Tony de Paula e demais colegas presentes eu vou trazer uma novidade a aproveitar o espaço que nos foi aberto, o Conselho Regional de Educação Física da Primeira Região, através da sua Câmara de Educação Física Adaptada Inclusiva, vem lançar esse ano já em fase de, processo de de impressão, o guia prático da pessoa com deficiência. Eu peço a gentileza de compartilhar, apenas a imagem já aprovada, pra que todos possam ver o que a gente está propiciando, seria a capa do nosso guia prático da pessoa com deficiência, e eu queria falar pouco desse guia, pra que a gente possa entender como que tanto o Conselho Federal de Educação Física, como essa estimada casa estão num pensamento. Igual, pensamento necessário, né? Quando a gente pensa no guia prático, esse guia ele tem como parceiros instituições renomadas, como a Ordem dos Advogados do Brasil, a Onda Autismo, a Suderj, o CONFEF, Conselho Federal de Educação Física, e o grande objetivo desse guia prático deputado, é que a gente possa ofertar aos profissionais de educação física de forma gratuita, acesso a informações mais qualificadas sobre as mais diversas deficiências. Então a gente traz no guia prático capítulo que fala sobre o capacitismo, pra que a gente possa ter essa quebra do preconceito direcionado a pessoas com deficiência, a gente traz capítulos que abordam deficiência intelectual, deficiência visual, deficiência auditiva, transtorno do espectro autista, deficiência física e doenças raras. Além de trazermos anexo onde a gente oferta uma ferramenta de anamnese para que os profissionais de educação física possam entender e reconhecer esse aluno ou esse cliente com deficiência que ele passa a atender. Esse guia ele traz informações sobre definições, CID, epidemiologia, faixa de segurança de intervenção, atividades prescritas e que principalmente o profissional de educação física ele tem material acessível, de fácil leitura, pra que ele possa se sentir cada vez mais seguro de ofertar uma educação física de excelência, estando na escola ou nos seus mais diversos espaços de execução profissional. Então a ideia desse material é que a gente possa ofertar informações técnicas de formas de de forma não segregada, são informações construídas tecnicamente, mas com uma uma fala mais simplória pra que a gente possa ter essa quebra de barreiras e não segregar o conhecimento, alcançando todos os profissionais de educação física pra que a gente possa potencializar justamente o que essa casa traz hoje em discussão. Como é importante a educação física, os os esportes adaptados, o estímulo motor social, internacional cognitivo pra que essas crianças com deficiência tenham primeiro a oportunidade de acesso à quebra de barreiras e não há espaço melhor do que o educacional pra que a gente possa ter essas quebras de barreiras de acesso, utilizandose da educação física como ferramenta fundamental no processo de construção social, quebra de barreiras e principalmente, pra que a gente possa estruturar uma sociedade mais plural, mais inclusiva e mais equânime. Então findando o meu período de fala, eu me torno tanto repetido mas de suma importância, mais uma vez agradecer ao deputado federal Otoni de Paula, agradecer ao meu amigo que vai falar daqui a pouco o Renato de Paula, agradecer a toda essa respeitada casa e respeitada comissão por entender como é importante cada vez mais sedimentarmos a educação física escolar, fortalecermos a educação física escolar pra que a gente possa ofertar uma ferramenta fundamental de transformação social, não só pras pessoas e crianças com deficiência que lá estão presentes, mas também pra que essas crianças neurotípicas que estão na escola tenham melhor entendimento sobre a inclusão dessas crianças com deficiência, que a gente tenha cada vez mais a quebra do capacitismo e a gente possa alcançar essa tão sonhada sociedade mais plural, equânime e inclusiva. Agradeço a palavra e grande abraço a todos que estão presentes e nos assistindo pela rede.",
      "summary": " Conselheiro do CREF1 valoriza educação física como ferramenta inclusiva e transformadora, combatendo evasão escolar e preconceitos. Lançará Guia Prático da Pessoa com Deficiência, oferecendo informações qualificadas a profissionais de educação física.",
      "speaker": {
        "name": "George Francisco de Lima Telles",
        "position": "Mestre em CAF e Conselheiro do Conselho Regional de Educação Física da 1ª Região (CREF1). - Conselho Regional de Educação Física da 1ª Região (CREF1)."
      }
    },
    {
      "start_time": 1715079318,
      "duration": 25,
      "transcription": "E e que deve ser não somente clamor seu, mas de outros pais, de outros responsáveis também, e de pessoas também com com deficiência ali em Feira de Santana na nossa querida Bahia, nós temos uma uma emenda de comissão não é? Que será destinada aos nossos deputados, membros membros efetivos desta desta desta douta comissão. No meu caso, eu sou eu sou, eu eu eu sou membro suplente desta comissão, não é? E parte desta emenda de comissão, é apenas para os os membros principais os membros efetivos. Eu acho que mais importante do que isso é você enquanto cidadão baiano poder bater na porta dos nossos gabinetes dos nossos colegas baianos, não é? Para que de forma individualizada, não é, e menos burocrática, não é isso aí quando é individualizada, eles possam entender sobre a importância da destinação desta desta desta desta verba não é, desta emenda parlamentar, para a construção desse centro social para pessoas especiais. Então fica esta minha dica obviamente que se você fosse do meu Rio de Janeiro esse apelo seria respondido não a nível de comissão mas a nível pessoal o que seria pra mim muito honroso está bom? Seja muito bemvindo sempre aqui J tá? Sucesso aí na sua caminhada política também na nossa feira de Santana, na nossa Bahia. Bem, eu quero agradecer imensamente a todos os nossos convidados que participaram desta desta. A todos que participaram deste nosso dessa nossa mesa de debate, que tratou sobre a importância dos esportes adaptados como ferramenta na redução da evasão escolar dos PCDs e crianças com autismo. Eu eu tenho certeza que tudo aquilo que foi debatido servirá como como subsídio para que não somente esse parlamentar, mas para que outros parlamentares interessados possam fazer nesta casa proposituras ou possam encaminhar ao próprio governo federal indicações legislativas no sentido desta desta inclusão e desta e deste e desta tentativa de impedirmos que a evasão escolar de PCDs e de crianças autismo se evoluam pela falta principalmente dos esportes adaptados. Quero imensamente agradecer a todos, fazer menção do senhor Sidinei da educação, não é isso? Que está também aqui conosco. Eu quero saudar também o nosso Sidinei, que é batalhador na área de inclusão também da cidade de de Simões Filho também na nossa Bahia, não é isso? Parabéns aqui aos nossos baianos pela representatividade aqui nessa comissão, desejo também ao Sidinei da educação, Silva Nei desculpe, ao meu querido Silva Nei da educação, sucesso também na sua caminhada Silva Nei. Deus te abençoe, sucesso, sucesso e sucesso. Bem, eu quero nesse momento agradecer a participação do professor José Ricardo Dávila e convidálo para as suas considerações finais. Depois a palavra, aliás do nosso professor George Francisco Lima Teles, que vai fazer as suas considerações, em seguida do doutor Renato de Paula para as suas considerações e concluiremos com o Clodoaldo Francisco da Silva também para as suas considerações. Professor George Francisco Lima Teles, muitíssimo obrigado pela sua participação que foi brilhante aqui representando também o nosso conselho regional de educação física e a sua experiência como membro e mestre, como mestre em Cafe, com certeza contribuiu muito pra esta audiência pública. Muito obrigado professor. Bom, eu que agradeço deputado, é grande",
      "summary": " Deputado propõe apelo à comunidade para pressionar deputados baianos a destinar verba de emenda parlamentar para construção de centro social para pessoas com deficiência, afirmando que como cidadão carioca, teria sucesso na abordagem pessoal. Discute importância de esportes adaptados para redução da evasão escolar de PCDs e crianças com autismo. Agradece a participação de convidados e convida professores para considerações finais.",
      "speaker": {
        "id": 204441,
        "name": "Otoni de Paula",
        "position": "Deputado"
      }
    },
    {
      "start_time": 1715079343,
      "duration": 3,
      "transcription": "Ciências da atividade física, ok. E",
      "speaker": {
        "name": "George Francisco de Lima Telles",
        "position": "Mestre em CAF e Conselheiro do Conselho Regional de Educação Física da 1ª Região (CREF1). - Conselho Regional de Educação Física da 1ª Região (CREF1)."
      }
    },
    {
      "start_time": 1715079346,
      "duration": 41,
      "transcription": "Também e conselheiro do Conselho Regional de Educação Física da Primeira Região CREF1. Professor Professor George, me permita lhe fazer três perguntas e aí o senhor com as com o seu poder de síntese poderá me responder. Qual a diferença pra que fique claro entre esportes adaptados e esporte para olímpicos? O senhor chegou a falar isso isso na sua fala. Quando a gente",
      "summary": " Deputado perguntou diferença entre esportes adaptados e esportes olímpicos ao Professor George.",
      "speaker": {
        "id": 204441,
        "name": "Otoni de Paula",
        "position": "Deputado"
      }
    },
    {
      "start_time": 1715079387,
      "duration": 71,
      "transcription": "Fala sobre esportes paralímpicos, a gente segue todo o regramento da paralimpíada. Então a gente utiliza das regras e e noções do do esporte paralímpico. Então a gente tem determinado balizamento de execução. Quando a gente fala de esportes adaptados, a gente pode adaptar qualquer estímulo, qualquer esporte existente e também os esportes paralímpicos de forma adaptada à realidade do público que será atingido. Exemplo muito simples é quando a gente fala, por exemplo, do esporte paralímpico golball, né, a gente precisa de traves nas dimensões corretas, a gente precisa de uma quadra nas dimensões corretas, a gente precisa da bola com guizo e quando a gente fala, por exemplo, de esporte adaptado, a gente pode adaptar, falando rapidamente, uma bola com saco plástico pra que a gente possa ter estímulo auditivo, a gente pode adaptar as baresas, então é simplesmente dar o acesso e adaptar à realidade tanto da instituição onde o profissional está como da turma que será atendida ou daquele cliente ou daquele aluno. Uma outra pergunta professor.",
      "summary": " Mestre em CAF e Conselheiro do CREF1 discutiu esportes paralímpicos e adaptados, seguindo regras paralímpicas e adaptando qualquer estímulo ou esporte à realidade do público atingido. Exemplificou com golball paralímpico e adaptações como bola com saco plástico e alterações nas barras para facilitar acesso.",
      "speaker": {
        "name": "George Francisco de Lima Telles",
        "position": "Mestre em CAF e Conselheiro do Conselho Regional de Educação Física da 1ª Região (CREF1). - Conselho Regional de Educação Física da 1ª Região (CREF1)."
      }
    },
    {
      "start_time": 1715079458,
      "duration": 25,
      "transcription": "",
      "speaker": {
        "id": 204441,
        "name": "Otoni de Paula",
        "position": "Deputado"
      }
    },
    {
      "start_time": 1715079483,
      "duration": 98,
      "transcription": "Fala de crianças neurotípicas, a gente fala de crianças sem deficiências, né? E aí quando a gente fala de crianças com deficiências eu acho que a gente não pode, deputado, se resumir apenas na sala de aula, né, hoje é é uma discussão muito ampla onde a gente precisa avançar como sociedade, a gente precisa avançar como, principalmente entender que a pessoa vem antes de qualquer limitação. Então a gente precisa de acessibilidade, falando especificamente da educação, a gente precisa de acessibilidade de materiais, a gente precisa de acessibilidade estrutural, a gente precisa de acessibilidade comportamental, a gente precisa de professores capacitados. Então, ter momento como esse, deputado, é primeiro passo de entendimento do quão precisamos ainda adaptar essas instituições e principalmente à sociedade. Quando a gente fala de pessoas com deficiências visuais, a gente precisa de materiais adaptados. Quando a gente fala de crianças com TEA, que é o autismo, dependendo da sua, por exemplo, hiper hipersensibilidade sensorial, a gente precisa de adaptações nas salas, a gente precisa de cuidado maior na na necessidade de mediação escolar, caso seja necessário, dependendo de cada aluno. Mas eu acho que ter espaços públicos de discussão, de entendimento que a gente precisa cada vez mais utilizarse desses espaços pra gente discutir acessibilidade, inclusão e principalmente deputado quebra de barreiras. Eu acho que isso que a gente tem que fomentar e estimular cada vez mais.",
      "summary": " Mestre em CAF e Conselheiro do CREF1 destacou a importância de acessibilidade em educação para alunos com deficiências, incluindo: adaptação de materiais, estrutural, comportamental; professores capacitados e mediação escolar se necessário. Promovemos inclusão e quebra de barreiras por meio de discussões e entendimento.",
      "speaker": {
        "name": "George Francisco de Lima Telles",
        "position": "Mestre em CAF e Conselheiro do Conselho Regional de Educação Física da 1ª Região (CREF1). - Conselho Regional de Educação Física da 1ª Região (CREF1)."
      }
    },
    {
      "start_time": 1715079581,
      "duration": 17,
      "transcription": "Quem é destinado esse guia prático, da pessoa com deficiência. Deputado federal",
      "speaker": {
        "id": 204441,
        "name": "Otoni de Paula",
        "position": "Deputado"
      }
    },
    {
      "start_time": 1715079598,
      "duration": 103,
      "transcription": "Paula, esse guia ele foi escrito pela Câmara de Educação Física Adaptada e Inclusiva do CREF a qual no momento eu sou o presidente. E a motivação da construção desse material foi de cada vez mais que o profissional de educação física tenha conhecimento para ter segurança na sua intervenção, pra que ele possa ofertar cada vez mais uma educação física de excelência. Então a gente buscou alguns parceiros que tivessem a contribuição intelectual, mas principalmente que tivessem o entendimento do qual a gente precisa ofertar cada vez mais conhecimento e preparação pra que esses profissionais de educação física possam intervir na sociedade. Então ele é guia lançado, escrito pela SEFAZ, que é a Câmara de Educação Física Adaptada Inclusiva e lançado pelo Conselho Regional de Educação Física do CREF sendo chancelado pelo Conselho Federal de Educação Física, pela Superintendência de Esporte do Rio de Janeiro, a Suderres, pela Onda Autismo, que é movimento hiper respeitado mundialmente, e pela Diretoria de Defesa da Pessoa com Deficiência da OAB na figura do meu querido e militante Geraldo Nogueira. Então, respondendo a sua pergunta e não mais me estendendo, esse material vai ser material gratuito que estará disponibilizado nas plataformas de todos os e de livre acesso na e de livre acesso na rede, a gente espera poder auxiliar demais profissionais que possam se beneficiar com esse conteúdo. Muito bom.",
      "summary": " Guia para professores de educação física, promovendo conhecimentos e segurança em intervenções adaptadas e inclusivas, oferecido gratuitamente por parceiros especializados, disponível em plataformas online.",
      "speaker": {
        "name": "George Francisco de Lima Telles",
        "position": "Mestre em CAF e Conselheiro do Conselho Regional de Educação Física da 1ª Região (CREF1). - Conselho Regional de Educação Física da 1ª Região (CREF1)."
      }
    },
    {
      "start_time": 1715079701,
      "duration": 129,
      "transcription": "Professor George Francisco de Lima, nós agradecemos vossa senhoria que vai estar ainda ainda conosco caso possa para que nós possamos estar ouvindo os outros participantes e aí demandar aí no final algum questionamento alguma pergunta do público que está nos acompanhando. Após o professor George Francisco de Lima Teles para continuar a mesa de debate desta nossa audiência pública, que tem como tema a importância dos esportes adaptados como ferramenta de redução da evasão escolar dos PCDs e crianças com autismo, eu convido a eu posso voltar com o Professor José Ricardo Dávila? Ainda não, né? Então nós vamos continuar e vamos com o Doutor Renato de Paula, pode ser? Doutor Renato de Paula, fisioterapeuta e mestre em PhD em bioquímica médica pela Universidade Federal do Rio de Janeiro. Ele é também PhD em neurociência pelo Imperial College em Londres, mas a sua maior virtude, o seu maior atributo é ser meu irmão biológico, não é? Então, então eu quero convidar para esta mesa de debate doutor Renato de Paula, meu irmão, meu irmão biológico que do qual eu tenho muito orgulho e que inspirou o nosso mandato desde vereador na Câmara Municipal da cidade do Rio de Janeiro ao olharmos para esse tema da inclusão social, principalmente na área do esporte e na área educacional com olhar mais meticuloso e mais e mais humano e mais cuidadoso. Doutor Renato, vossa senhoria dispõe do tempo de dez minutos para a sua exposição.",
      "summary": " Deputado convida fisioterapeuta e irmão, Doutor Renato de Paula, a discutir importância de esportes adaptados para reduzir evasão escolar de PCDs e crianças com autismo, com 10 minutos de apresentação.",
      "speaker": {
        "id": 204441,
        "name": "Otoni de Paula",
        "position": "Deputado"
      }
    },
    {
      "start_time": 1715079830,
      "duration": 594,
      "transcription": "Bom dia aos ouvintes, bom dia a essa seleta mesa. Bom dia deputado federal o Tony de Paula e meu irmão, de sangue e de luta por essa iniciativa. Passo a minha saudação ao nosso campeão paralímpico, Clodoaldo Silva, ao nosso querido professor Jorge Teles, ao nosso querido Wagner Bezerra ao querido Jorge que explanou tão bem a importância do profissional de educação física. Trago a saudação do meu conselho Conselho Regional de Fisioterapia e Terapia Ocupacional do Rio de Janeiro, e da ABFC Associação Brasileira de Futebol em Cadeiras de Rodas, no qual eu sou o diretor científico. Com essa saudação eu agradeço a presença da iaks a nossa intérprete de libras, que está fazendo essa audiência pública ser o mais acessível pra que essa informação chegue a todos os públicos. Falar de esporte adaptado no Brasil, infelizmente é lembrar de vale de ossos secos. É algo que nada temos a celebrar, ainda assim somos o segundo melhor país do mundo em medalhas paralímpicas, Isso reflete o quanto a gente ainda poderia ser uma potência muito maior, se as escolas realmente nos fornecessem os para atletas através da iniciativa de esporte adaptado. Eu começo lamentando, citando alguns números, durante a pandemia, a cada dez estudantes com deficiência, apenas recebeu algum suporte. Cinquenta e nove por cento dos estudantes com deficiência dizem nunca terem recebido nenhum suporte adaptado para as suas aulas regulares, não estou me referindo ainda às aulas adaptadas ao esporte. Quando perguntado os pais se eles acham que os filhos completarão aquele ciclo do ano letivo, vinte e oito por cento dos pais com filhos com deficiência, incluindo eles as pessoas autistas que são pessoas com deficiência, vinte e oito por cento desses pais acreditam que o filho não conseguirá concluir. Apenas dezenove por cento dos filhos sem deficiência tem a mesma crença. Então, a barreira arquitetônica ela é real, mas hoje nós temos uma grande barreira comunicacional, e o senhor começou muito bem, explanando a importância dessa audiência pública, uma das poucas coisas que não mudou em todos os anos é a forma que educamos, e educamos todas as pessoas como se elas tivessem a mesma funcionalidade. Isso é capacitismo, é não olhar que as pessoas são distintas, e não oferecer pras pessoas distintas ferramentas de educação. Falando mais especificamente do esporte adaptado e do Rio de Janeiro, nós enfrentamos aqui na nossa cidade, a lácema do nosso secretário de educação comemorar de a quatro estudantes com autismo têm mediador, ou seja, no Rio de Janeiro se comemora que setenta e cinco por cento das crianças autistas não têm mediador, quiçá falar de esporte adaptado, temos muito pouco a celebrar. A iniciativa que eu pude contribuir durante a minha estada como presidente da Suderj, que terminei há algumas semanas, foi uma instituição que tem selo olímpico para promover o esporte globalmente e tem aqui no Rio de Janeiro a sua representatividade e essa parceria entre a espécie olímpicos com a Suderj permitiu que professores da rede estadual possam no futuro breve se formar em esporte adaptado Eu falo isso e o professor George, os professores aqui presente em educação física, podem corrigir a minha fala, como fisioterapeuta, porque há uma escassez na nossa graduação, que pouco fala de esporte adaptado. Eu falo como fisioterapeuta, mas tenho certeza que essa escassez também na educação física e nas outras áreas de saúde. E eu peço a ajuda, eu sei que o senhor ainda está envolvido com isso, o deputado federal Otônio de Paula, para ir ao MEC e pedir ao MEC que faça uma revisão do currículo básico exigido para as áreas de saúde, Médicos, fisioterapeutas, professores de educação física, fonoaudiólogos, terapeutas ocupacionais, deveriam saber da importância do esporte adaptado como ferramenta de saúde. O que nós aprendemos como ferramenta de saúde infelizmente é sobre medicamento ou intervenção cirúrgica e sendo que científicamente está comprovado que quem faz esporte além da socialização melhor acelerada além do descaminho para o crime organizado para as práticas que não conduzem com a cidadania, além de permitir que essas pessoas encontrem o pertencimento, o grupo, pra pessoa com deficiência é crucial ela ter espelho, ela ter referências de pessoas de sucesso. Isso na escola evita termos poucos dados no Rio de Janeiro ou no Brasil, científico, mas dados mundiais apontam que escolas adaptadas ao esporte reduzem a sua evasão escolar em até sessenta por cento, isso é muito, ou seja, a criança que faz o esporte adaptado, o adulto que na universidade faz o esporte adaptado, se encontra entre os seus e tem menor dificuldade de permanecer e concluir o seu ensino. Então é crucial que das universidades ao ensino primário nós tenhamos maior fomento, seja na grade curricular, ou o maior incentivo que profissionais concursados, ao menos esses, todos têm uma formação extracurricular em como lidar com esses estudantes. Reforço isso, lembrando da cartilha que a Suderge em colaboração com o CREF, de autoria do professor George, disponibiliza pra os seus professores, a falta de informação faz com que uma boa intenção mal direcionada coloque esse aluno em maior capacitismo ainda, ou seja, se o esporte não é adaptado, ele se torna terreno inóspito pra pessoa com deficiência. E eu encerro a minha fala lembrando novamente dos jogos da Special Olympia, que são jogos mistos, ou seja, não se faz nicho, esporte apenas para pessoas com deficiência. Pessoas com deficiência e pessoas ditas sem deficiência jogam o mesmo jogo, obviamente, com todas as regras para que haja equilíbrio. Isso deveria estar nas escolas municipais, isso deveria estar nas escolas estaduais, isso deveria estar nas escolas federais como algo normal para que o nosso olhar capacitista e de desconforto perante a pessoa com deficiência seja reduzido até se extinguir. Podemos transformar problemas em potência através do esporte. Agradeço muito deputado, novamente celebro, eu acredito que talvez o senhor seja a vanguarda nessa Câmara dos Deputados em trazer tema tão nobre e tão importante, e eu espero que haja aí uma audiência de muitos deputados, caso contrário, a gente vai estar confirmando que a pessoa com deficiência continua à sombra, continua invisível, até mesmo para os nossos parlamentares. Que bom que elas não são invisíveis para o senhor. Muito obrigado. Eu eu é que",
      "summary": " Fisioterapeuta, Mestre e PhD em Bioquímica: saúda participantes, inclui pais e atletas com deficiência; lamenta falta de suporte a estudantes com deficiência durante pandemia; destaca barreiras arquitetônicas e de comunicação como desafios; propõe melhor educação sobre esporte adaptado em áreas de saúde; emphasizes importance of esporte adaptado em reduzir evasão escolar e criar inclusão.",
      "speaker": {
        "name": "Renato de Paula",
        "position": "Fisioterapeuta, Mestre e PhD em Bioquímica Médica - Universidade Federal do Rio de Janeiro"
      }
    },
    {
      "start_time": 1715080424,
      "duration": 82,
      "transcription": "Doutor Renato de Paula até por ter nos inspirado no exercício dos nossos mandatos a este tema de fundamental importância para a sociedade brasileira e principalmente para as nossas crianças e adolescentes. Continuando a nossa audiência pública, eu convido para a mesa de debate o nosso atleta paraolímpico orgulho nacional Clodoaldo Francisco da Silva Correia, que hoje é consultor em acessibilidade e inclusão, e também é colunista do portal UOL. Clodoaldo é com muita alegria que eu lhe passo a fala e vossa senhoria terá a fala pelo tempo de dez minutos. O seu microfone está mudo, eu acho que você precisa abrilo aí. Vai, Não ainda ainda mudo ainda mudo. Você tem que clicar opa agora sim. E agora Agora sim, meu atleta favorito.",
      "summary": " Deputado convida atleta paralímpico, consultor em acessibilidade e colunista do UOL, Clodoaldo Francisco da Silva Correia, a se dirigir à mesa de debate durante 10 minutos; ele teve problemas técnicos com o microfone, mas foi resolvido.",
      "speaker": {
        "id": 204441,
        "name": "Otoni de Paula",
        "position": "Deputado"
      }
    },
    {
      "start_time": 1715080506,
      "duration": 594,
      "transcription": "Obrigado deputado federal Otónio de Paula, também saldo né, essa mesa seleta e fico feliz. Quando dessa audiência onde trata o esporte adaptado o esporte inclusivo. Eu que fui atleta paraolímpico de noventa e oito a dois mil e dezesseis, foram dezoito anos nadando, competindo dentro do Brasil, fora dele, ganhando 14 medalhas seis ouros seis pratas e dois bronzes e em casa são mais de 700 medalhas e eu brinco se eu não der essa medalha eu comprava mas eu trazia galera mas antes de falar sobre essa inclusão sobre a sensibilidade no esporte adaptado Esporte paraolímpico sou Clodoaldo Silva lá de Natal no Rio Grande do Norte sou uma pessoa de cor morena olhos e cabelos castanhos e o senhor né deputado Antônio de Paula falou que realmente eu sou campeão paralímpico, sou consultor em acessibilidade de inclusão e atualmente estou na vicepresidência de esportes e saúde da sudeste a superintendência de esportes do estado do Rio de Janeiro estou desde agosto do ano passado essa essa função e esse cargo da sudeste lá atrás era do nosso querido né meu amigo e o teu irmão Renato de Paula que eu mando beijão que está aqui também que falou maravilhosamente bem o professor George o professor Ricardo vai já falar também. Então estou na vicepresidência de esportes e saúde da Sudeg, E hoje nós temos o nosso querido Marcão né nosso presidente e falar pouco e porque eu gosto de falar pouco da minha carreira da minha trajetória esportiva eu nasci com uma paralisia cerebral falta de oxigenação durante o parto minhas pernas eram cruzadas e dobradas e ao longo da minha infância foi fazendo várias cirurgias para poder esticar as pernas para poder desdobrar as pernas e aos 16 anos fiz a minha última cirurgia e o meu médico recomendou a natação não para eu ser atleta não pra eu viajar o Brasil não pra eu viajar o mundo, mas apenas como fisioterapia como reabilitação E ali eu me encontrei, ali eu entrei no esporte, ali naquele momento eu sabia que os atletas paraolímpicos do Rio Grande do Norte também nadavam naquela piscina e pintou aquele pensamento de poder eu posso ser atleta comecei a trilhar comecei a me dedicar comecei a competir comecei a ganhar medalhas e como eu falei em noventa e oito foi meu primeiro campeonato Mas eu acredito que o boom do esporte para o Olímpico foi em dois mil e quatro quando aconteceu jogos para olímpicos de Atenas e ali o Brasil saiu com 14 medalhas de ouro e só dali daquela edição paraolímpica eu saí com seis medalhas de ouro e uma de prata e porque eu falo que ali foi o boom do Esporte para o Olímpico e divisor de águas porque ali pela primeira vez a mídia seja escrito seja televisivo seja os sites a internet que já estava começando começou a mostrar pessoas com deficiência. Se alegrando se ganhava medalhas chorando e ficando triste se perdiam medalhas então ali o Brasil passou a ver que nós pessoas com deficiência nós também a gente consegue buscar os nossos resultados e os nossos objetivos e o mais legal porque eu sempre falo de 2004 porque não foi bom só para o esporte para o Olímpico E aí é onde eu quero chegar foi muito bom também para o segmento das pessoas com deficiência e apesar de eu ter sido atleta ganhador de várias e várias medalhas eu eu acredito na educação eu acredito na escola no esporte eu acredito no esporte não para ser atletas mas no esporte como inclusão e justamente né estando junto lá atrás né eu na vicepresidência o Renato de Paula na presidência hoje nós temos o Marcão a suberge fez inúmeros eventos do ano passado para cá justamente enfatizando não o autorrendimento não enfatizando medalhas de ouro não enfatizando o lugar mais alto do pódio mas enfatizando através do esporte a inclusão da pessoa com deficiência da pessoa com autismo da pessoa com síndrome de Down ou seja quaisquer sejam a deficiência e o esporte se hoje eu realizo palestras por todo o Brasil se hoje eu estou numa vicepresidência da Sudésio se hoje eu sou comentarista do grupo Globo é para esportes para olímpicos tudo se deve a o esporte que eu entrei não para querer ser atleta mas eu entrei para melhorar minha qualidade de vida melhorar minha locomoção então o esporte nos traz essa oportunidade e nos traz principalmente para pessoas com deficiência a liberdade e foi isso que me trouxe porque cara lá de Natal no Rio Grande do Norte e onde nasceu o bairro dele é muito mais conhecido pela criminalidade e a violência que é bairro de Periferia é o bairro de Manuisa então aquele cara conseguiu conhecer o Brasil e o mundo através justamente do esporte então por isso que eu acredito e ter essa oportunidade de poder estar expondo testemunhando toda a minha vivência para outras pessoas que estão nos vendo é justamente falar cara e eles pensarem cara se o Clodoaldo conseguiu com todas essas dificuldades cara que tinha todas as justificativas cara que tinha todas as desculpas do mundo cara que poderia se fazer vítima não fez e ele conseguiu eu também posso conseguir e recado né que a galera que está nos escutando de todos os segmentos os nossos professores é pessoas que querem entrar na educação física também quando vê alguma pessoa com deficiência seja qual for a deficiência não impõe a limite para elas não impõem limites para elas deixa ela ir lá e fazer porque porque eu falo isso porque isso Deputado aconteceu comigo né muitas vezes eu e o pensamento cara eu não vou conseguir fazer aquilo e o meu treinador meu técnico meu professor de educação física ele chegava vai lá e faz faz o teu melhor e aí eu fazia e conseguia então muito ao esporte adaptado muito ao esporte paraolímpico claro que a gente tá quebrando os paradigmas mas justamente antes vi uma pessoa com deficiência como uma pessoa frágil e nós não somos pessoa não somos pessoas frases nós somos pessoas que buscamos a igualdade buscamos não peninha mas buscamos oportunidades para que a gente possa estar mostrando as nossas capacidades e potencialidades e finalizando aqui é deputado vocês ficaram com medo de eu estourar o tempo né mas se eu coloquei o computador ali estou colocando bem grandão pra não estourar o tempo deputado então pra finalizar quero agradecer muito a oportunidade que eu tive de poder estar conhecendo o Renato de Paula né toda essa galera da Supese mas também ter oportunidade deputado autônomo de Paula conhecer você também tá abraçando e acolhendo esse segmento da pessoa com deficiência e também agradecer pelas emendas né parlamentares que você é também disponibiliza para o praia para todos que na região dos Lagos conseguimos ter né o praia para todos não só na região dos Lagos mas na cidade do Rio de Janeiro então pra finalizar é isso, obrigado e estou por aqui. Meu amigo Clodoaldo Francisco da Silva Correia, a sua participação traz brilhante.",
      "summary": " Ex-atleta paralímpico e vice-presidente de esportes e saúde da Sudeg, Clodoaldo Francisco da Silva Correa, ressalta importância de mudar paradigmas sobre esporte adaptado, vendo pessoas com deficiência como capazes e buscando oportunidades. Ganhou 14 medalhas em Jogos Paralímpicos e defende inclusão social por meio do esporte, agradecendo emendas parlamentares para \"praia para todos\" no Rio de Janeiro e região dos Lagos.",
      "speaker": {
        "name": "Clodoaldo Francisco da Silva Correa",
        "position": "Consultor em acessibilidade e inclusão e colunista do portal UOL - UOL"
      }
    },
    {
      "start_time": 1715081100,
      "duration": 92,
      "transcription": "Imenso a esta a esta a esta audiência da nossa comissão de educação debatendo a importância do esporte adaptado como ferramenta de redução da evasão escolar dos PCDs e crianças com autismo, já que você viveu e vive na pele esta esta condição, e também esta superação, transformando problema em potência. Parabéns, parabéns de verdade. Nós já estamos chegando quase AAAA este término deste nosso debate, mas temos a honra de ter aqui conosco, participando também dessa nossa audiência pública, cidadão brasileiro que ao saber dessa nossa audiência veio aqui à câmara e como esta casa é a casa do povo pertence ao povo o povo tem voz com certeza. Estou falando de JRIOS. JRIOS é presidente do Instituto Nacional de Crianças com com Síndrome, também suplente de deputado estadual pela nossa querida Bahia. J vossa senhoria terá o tempo de três minutos para a sua exposição Fique à vontade esse tempo vai estar ali naquele visor. Bom dia a todos",
      "summary": " Deputado elogia importância do esporte adaptado para reduzir evasão escolar de pessoas com deficiência e autismo, referindo sua própria superação pessoal. Instituto Nacional de Crianças com Síndrome participa da audiência pública, com JRIOS, suplente de deputado estadual pela Bahia, falando por três minutos.",
      "speaker": {
        "id": 204441,
        "name": "Otoni de Paula",
        "position": "Deputado"
      }
    },
    {
      "start_time": 1715081192,
      "duration": 155,
      "transcription": "Em primeiro lugar, quero saudar a mesa na pessoa do deputado Otônio de Paula, meu amigo, recentemente viajou a Feira de Santana e visitou a nossa igreja Renovame receba os abraços do pastor Joelson e de toda a comunidade de Feira de Santana. Pra mim é uma honra estar aqui participando com com os senhores, com vossa excelência, de tema tão importante, que é os PCDs, autistas e síndromes, pessoas que têm síndromes. Eu sou pai, de uma criança com síndrome de Down, que passou quatro meses na UTI, e fez três cirurgias, e eu vi a dificuldade que essas pessoas passam, os pais e também as crianças. E eu e nós não temos centros específicos, nem desportivos, nem educacionais hoje na Bahia, para acolher esse público. Então por iniciativa da comunidade, por minha iniciativa, criamos o Instituto Nacional de Crianças com Síndrome, e o esporte ele é fundamental para interação e integração entre as pessoas. Eu tenho uma pergunta, não vou estourar o tempo, a pergunta específica para a comissão da educação na pessoa do deputado Antônio de Paula. Meu amigo, qual a possibilidade, qual a possibilidade da comissão enviar uma emenda para a Feira de Santana, para a gente construir o nosso centro do Instituto Nacional de Crianças com Síndrome. Há possibilidade da comissão enviar uma emenda específica através do instituto ou de uma associação que temos também que somos presidente, que é a, eu sou presidente e atual presidente da Associação Brasileira de Literatura e Artes. E dentro das escola e dos debates lá em Salvador, na casa de Angola, em outros lugares que a gente representa a Feira de Santana e região, a gente não não tem esse debate, não tem abertura porque a gente também não tem centros de debates e não tem centro desportivos para as crianças, os PCDs, autistas e síndrome de Down, essa é a minha solicitação aqui diante do senhor, pela necessidade mesmo da gente ter centro e das novas arenas também Feira de Santana e região a gente consiga ter espaço destinado através de uma emenda pra gente construir espaço definitivo para as crianças com síndromes. J respondendo a sua a sua importante pergunta e",
      "summary": " Instituto criado por iniciativa comunidade para aiding PCDs, autistas, e síndromes; fundador petitions education commission for a center in Feira de Santana.",
      "speaker": {
        "name": "J. Rios",
        "position": "Instituto Nacional de Crianças com Sindrome"
      }
    },
    {
      "start_time": 1715081347,
      "duration": 331,
      "transcription": "E e que deve ser não somente clamor seu, mas de outros pais, de outros responsáveis também, e de pessoas também com com deficiência ali em Feira de Santana na nossa querida Bahia, nós temos uma uma emenda de comissão não é? Que será destinada aos nossos deputados, membros membros efetivos desta desta desta douta comissão. No meu caso, eu sou eu sou, eu eu eu sou membro suplente desta comissão, não é? E parte desta emenda de comissão, é apenas para os os membros principais, os membros efetivos. Eu acho que mais importante do que isso é você enquanto cidadão baiano poder bater na porta dos nossos gabinetes dos nossos colegas baianos, não é? Para que de forma individualizada, não é, e menos burocrática, não é isso aí quando é individualizada, eles possam entender sobre a importância da destinação desta desta desta desta verba não é, desta emenda parlamentar, para a construção desse centro social para pessoas especiais. Então fica esta minha dica obviamente que se você fosse do meu Rio de Janeiro esse apelo seria respondido não a nível de comissão mas a nível pessoal o que seria pra mim muito honroso está bom? Seja muito bemvindo sempre aqui J tá? Sucesso aí na sua caminhada política também na nossa feira de Santana, na nossa Bahia. Bem, eu quero agradecer imensamente a todos os nossos convidados que participaram desta desta. A todos que participaram deste nosso dessa nossa mesa de debate, que tratou sobre a importância dos esportes adaptados como ferramenta na redução da evasão escolar dos PCDs e crianças com autismo. Eu eu tenho certeza que tudo aquilo que foi debatido servirá como como subsídio para que não somente esse parlamentar, mas para que outros parlamentares interessados possam fazer nesta casa proposituras ou possam encaminhar ao próprio governo federal indicações legislativas no sentido desta desta inclusão e desta e deste e desta tentativa de impedirmos que a evasão escolar de PCDs e de crianças autismo se evoluam pela falta principalmente dos esportes adaptados. Quero imensamente agradecer a todos, fazer menção do senhor Sidinei da educação, não é isso? Que está também aqui conosco. Eu quero saudar também o nosso Sidinei, que é batalhador na área de inclusão também da cidade de de Simões Filho também na nossa Bahia, não é isso? Parabéns aqui aos nossos baianos pela representatividade aqui nessa comissão, desejo também ao Sidinei da educação, Silva Nei desculpe, ao meu querido Silva Nei da educação, sucesso também na sua caminhada Silva Nei. Deus te abençoe, sucesso, sucesso e sucesso. Bem, eu quero nesse momento agradecer a participação do professor José Ricardo Dávila e convidálo para as suas considerações finais. Depois a palavra, aliás do nosso professor George Francisco Lima Teles, que vai fazer as suas considerações, em seguida do doutor Renato de Paula para as suas considerações e concluiremos com o Clodoaldo Francisco da Silva também para as suas considerações. Professor George Francisco Lima Teles, muitíssimo obrigado pela sua participação que foi brilhante aqui representando também o nosso conselho regional de educação física e a sua experiência como membro e mestre, como mestre em Cafe, com certeza contribuiu muito pra esta audiência pública. Muito obrigado professor. Bom, eu que agradeço deputado, é grande",
      "summary": " Deputado propõe apelo à comunidade baiana para solidariedade com pessoas especiais em Feira de Santana, destacando importância de destinar verba para centro social e promover esportes adaptados, evitando evasão escolar de PCDs e crianças com autismo.",
      "speaker": {
        "id": 204441,
        "name": "Otoni de Paula",
        "position": "Deputado"
      }
    },
    {
      "start_time": 1715081678,
      "duration": 77,
      "transcription": "",
      "speaker": {
        "name": "George Francisco de Lima Telles",
        "position": "Mestre em CAF e Conselheiro do Conselho Regional de Educação Física da 1ª Região (CREF1). - Conselho Regional de Educação Física da 1ª Região (CREF1)."
      }
    },
    {
      "start_time": 1715081755,
      "duration": 44,
      "transcription": "Professor José, aliás George Francisco de Lima Teles, apenas justificando que estaria também na nossa mesa o professor José Ricardo Dávila, mas infelizmente por questões técnicas ele não pôde participar, mas nós agradecemos a sua a sua voluntariedade em em participar deste deste deste debate. Passando a palavra para o doutor Renato de Paula para as suas considerações finais nesse debate sobre a importância dos esportes adaptados como ferramenta na redução da evasão escolar dos PCDs e crianças com autismo. Doutor Renato. Deputado Antônio de",
      "summary": " Deputado menciona justificativa ausência um participante, agradece sua disposição e passa a palavra para considerações finais sobre importância esportes adaptados na redução evasão escolar PCDs e autismo.",
      "speaker": {
        "id": 204441,
        "name": "Otoni de Paula",
        "position": "Deputado"
      }
    },
    {
      "start_time": 1715081799,
      "duration": 158,
      "transcription": "Eu agradeço a todos os membros da mesa, a quem ajudou a essa audiência acontecer, os funcionários das Câmara dos Deputados, ao Ezequias que desde sempre vem sendo braço direito pra o seu mandato. Eu quero finalizar agradecendo também aos funcionários aqui do Rio de Janeiro, tanto da Rocinha quanto do Sampaio, são dois complexos esportivos que nós podemos tornar como referência em esporte adaptado aqui no Rio de Janeiro, não é simples, é complexo, precisamos destinar tempo, informação, só com informação haverá conexão com as pessoas com deficiência. A conexão é que gera o afeto, e esse afeto permitirá a inclusão. O que está acontecendo hoje é que para se cumprir uma lei se joga as crianças nas escolas, se joga as crianças nas quohas esportivas e simplesmente a inclusão não ocorre porque esses três passos anteriores não são cumpridos primeiro se informa e se informa muito para gerar uma conexão só depois se gera empatia para que a gente tenha mais e mais esporte adaptado e esse esporte adaptado ele tem uma capacidade de se autocriar enorme como George disse você pode adaptar uma bola enrolada num plástico pra substituir uma bola de guizo que é muito cara para uma pessoa cega simplesmente jogar e se divertir com os outros que os nossos professores sejam incentivados e por fim toda a mazela que a gente tem na saúde hoje se dá pelo processo inflamatório devido ao nosso estilo de vida sedentário e má alimentação Isso é ainda pior para as pessoas com Isto é ainda pior para as pessoas com deficiência dentre elas deficiência intelectual e autismo ou seja, nós precisamos desinflamar os nossos estudantes para que eles aprendam mais durma melhor tenham menos necessidade de tela, tenham menos crises, quem vai fazer isso é o esporte. Eu espero que essa audiência pública seja uma ferramenta de uma construção de uma sociedade mais equânime que o Rio de Janeiro seja maravilhoso, porque ele é inclusivo. Doutor Renato, mais uma vez muitíssimo obrigado pelas",
      "summary": " Fisioterapeuta, Mestre e PhD em Bioquímica Médica - Universidade Federal do Rio de Janeiro agradece a todos presentes, destaca a importância de informação e conexão para inclusão em esporte adaptado, e enfatiza o papel do esporte na melhora da saúde, especialmente para pessoas com deficiência, como forma de \"desinflamar\" e promover aprendizado.",
      "speaker": {
        "name": "Renato de Paula",
        "position": "Fisioterapeuta, Mestre e PhD em Bioquímica Médica - Universidade Federal do Rio de Janeiro"
      }
    },
    {
      "start_time": 1715081957,
      "duration": 46,
      "transcription": "Participação nesta audiência pública, inspirada por vossa senhoria. Eu finalizo essa nossa rodada de considerações finais com o último debatedor, o último mas não mas não menos importante, pelo contrário, é o nosso orgulho nacional, o nosso atleta paraolímpico, Clodoaldo Francisco da Silva que deu aqui o seu testemunho não é? Ele que é uma pessoa com deficiência e que transformou problema em potência. Parabéns querido Clodoaldo da sua vida inspira a todos nós. Obrigado mais uma vez deputado.",
      "summary": " Deputado agradece participação em audiência, inspirado pela pessoa que transformou deficiência em força, orgulho nacional e atleta paralímpico Clodoaldo Francisco da Silva.",
      "speaker": {
        "id": 204441,
        "name": "Otoni de Paula",
        "position": "Deputado"
      }
    },
    {
      "start_time": 1715082003,
      "duration": 155,
      "transcription": "Otonite Paula. E aqui eu posso ficar por último, eu não poderia ficar na piscina, nas competições. Deputado, aqui está de boa. Mas agradeço, né? E como eu falei anteriormente, a galera que está nos vendo, empresas privadas, públicas, o parlamento brasileiro, a Câmara dos Deputados quando traz esse debate através do senhor né, o Renato de Paula que estamos mais próximos aqui com os nossos projetos e objetivos também. Então fico muito feliz e eu acho que justamente o eu não sou mais atleta desde dois mil e dezesseis quando eu finalizei a minha carreira nos Jogos Paraolímpicos Rio dois mil e dezesseis quando eu costumo dizer além de ter ganhado uma medalha eu costumo dizer que eu fui o cara que pus fogo no Maracanã assinei da dos jogos e o dois mil e dezesseis. E aí, pegando pouquinho daquela cerimônia de abertura, eu na minha cadeira de rodas, carregando a tocha para ali que fica pra poder acender a pira. E chega num determinado local no Maracanã. A pira está lá em cima, e entre mim e ela, tem degraus, tem escadas, e de repente abremse rampas dentro dos degraus e através das rampas eu subo e consigo acender a pira paralímpica dos jogos. E qual que foi a mensagem naquela cerimônia de abertura? A mensagem foi, pode haver escadas? Pode haver degraus? Podem. Mas se houver uma rampa todo mundo chega no mesmo lugar. Então E COLOCANDO E COLOCANDO MINHAS finais, A IMPORTÂNCIA DA ACESSIBILIDADE, A IMPORTÂNCIA DA INCLUSÃO pra que a gente, se não for grandes atletas campeões, mas que a gente possa ter cidadania e respeitabilidade. E eu tenho certeza que justamente essa audiência traz esse olhar, traz essa preocupação da Câmara dos Deputados, dos nossos parlamentares pra poder proporcionar, seja no esporte, seja na educação, seja em todo qualquer que seja o segmento, a acessibilidade para pessoas com deficiência. Muito obrigado deputado federal Otoni de Paula. Nós",
      "summary": " Consultor em acessibilidade e inclusão: A importância da acessibilidade e inclusão garante chegada ao mesmo lugar para todos, mesmo com obstáculos, promovendo cidadania e respeitabilidade para pessoas com deficiência em diferentes segmentos, como esporte e educação.",
      "speaker": {
        "name": "Clodoaldo Francisco da Silva Correa",
        "position": "Consultor em acessibilidade e inclusão e colunista do portal UOL - UOL"
      }
    },
    {
      "start_time": 1715082158,
      "duration": 409,
      "transcription": "Agradecemos querido Clodoaldo Francisco. Meus amigos em nome desta comissão quero agradecer a participação de todos os nossos convidados, quero agradecer a você que nos acompanhou pelos canais de comunicação da nossa Câmara Federal, vocês que nos honraram com as suas exposições, esclarecimentos e acompanhamento desta nossa audiência pública que, repito, debateu a importância dos esportes adaptados como ferramenta na redução da evasão escolar dos PCDs e crianças com autismo. Eu agradeço de forma muito especial as nossas servidoras, competentíssimas dessa comissão, a querida Fátima, a querida Letícia, a querida Elínia, eu falei certo, Elínia e também a querida Ana Lúcia, sem elas nós não conseguiríamos fazer esta audiência pública como nós fazemos. Aliás, esta é uma casa de excelentes servidores públicos, da mais capacidade. Queremos também de uma forma muito especial agradecer a esta pessoa gentil, maravilhosa e querida que eu tenho o prazer de estar conhecendo hoje, que é a querida iatsa eu acho que eu falei o nome certo iatsa ok muito bem que foi a nossa intérprete de libras aqui nesta audiência pública muito muito obrigado querida e tá bom? Muito bem. Podem abrir agora a tela única, por favor? E eu já me despeço da iatza. Meus amigos antes de nós encerrarmos esta audiência pública eu gostaria de abrir uma uma exceção nesse momento, para as considerações do meu querido colega e amigo de parlamento deputado Pompeu de Matos. Pompeu é dos mais brilhantes representantes da bancada federal de deputados federais do nosso glorioso Rio Grande. Rio Grande do Sul Estado conhecido pelas suas glórias, conhecido pela sua pujança, conhecido como povo corajoso e audais enfrentou a maior calamidade o maior acidente natural já registrado na história brasileira. O que aconteceu com o nosso Rio Grande é algo que nós deveremos lamentar por décadas e por que não dizer por alguns séculos. O que aconteceu com o nosso Rio Grande é sem precedente, repito, na história brasileira e talvez tenha acontecido isso pouquíssimas vezes na história mundial o que aconteceu na verdade poderia ter gerado muito mais mortes do que o número que infelizmente nós ainda registraremos de fatalidades do povo do Rio Grande. Agora, todo o Brasil se volta para a dor do nosso Rio Grande do Sul. Esta Câmara Federal, o Senado Federal e o Governo Federal devem esta semana se unir para levar pouco de alívio através de recursos financeiros, de recursos públicos para soerguermos o nosso Rio Grande do Sul. Eu sou daqueles querido Pompeu de Matos, que faço couro que nós devemos em momento de exceção como nós estamos vivendo, usar de todos os recursos que nós parlamentares temos. E eu digo de parte da nossas emendas, que nós destinamos exclusivamente aos nossos estados, mas nesse momento todos nós somos do Rio Grande do Sul. E também, e também, dos recursos do fundo eleitoral, que nós temos para usar este ano. Se nós nos unirmos e se nós tirarmos desse recurso, deste fundo bilionário, se nós retirarmos vinte por cento, já será grande alívio que nós poderemos colocar recurso amanhã, amanhã, já que é o recurso já destinado e que já está separado para as próximas eleições. Se nós fizermos esses pequenos gestos, mas que serão de fundamental importância para o nossos patriotas do Rio Grande do Sul, nós demonstraremos nesta casa a nós o nosso espírito público e a importância que nós temos e o nosso olhar humano para o Rio Grande do Sul que poderia ser o meu Rio de Janeiro, que poderia ser qualquer outro estado da nossa federação. Por isso nesse momento especial nós abrimos os microfones desta comissão de educação pós audiência pública para o nosso querido Pompeu de Matos. Pompeu, vossa excelência de explorar o tempo necessário, que lhe convier para falar em nome do povo do Rio Grande do Sul.",
      "summary": " Deputado agradece participantes e servidores da audiência pública sobre esportes adaptados. Ele also expresses sympathy for the natural disaster in Rio Grande do Sul, calling for federal support and use of parliamentary resources to help the state.",
      "speaker": {
        "id": 204441,
        "name": "Otoni de Paula",
        "position": "Deputado"
      }
    },
    {
      "start_time": 1715082567,
      "duration": 343,
      "transcription": "Obrigado deputado Otônio de Paula, agradeço a Deus por estar aqui vivo e em nome do povo gaúcho poder retornar ao Parlamento Federal depois de uma semana, uma semana assim de dor, de angústia, de choro, de tragédia, de catástrofe que o Rio Grande do Sul enfrentou. Agradeço as palavras de vossa excelência, deputado Antônio de Paulo sempre generoso, aliás, o Rio de Janeiro sempre generoso com o Brasil, e não é diferente com o Rio Grande do Sul, nossa velha capital, a cidade maravilhosa, mas deputado Antônio de Paulo Rio Grande está sofrendo. Olha, o que eu vi lá eu não imaginei que eu iria viver pra ver, histórias que contavam de mil novecentos e quarenta e que Porto Alegre estava debaixo d'água, Tudo que era no início do século de mil novecentos e cinco dez, tudo que era rio, voltou a ser rio. E aí invadiu toda a orla, é uma coisa assim impressionada, é como se o Rio de Janeiro, que tem aterro do Flamengo, o mar voltasse a ser o que era antes, imagine o Rio de Janeiro, o mar voltando a ser o que era antes dos aterros do Flamengo, ali na na Barra da Tijuca, Copacabana, Leblon, então isso é o que aconteceu, o que era o que era antigamente chama rua da praia virou rua da praia. A rua da praia que é o centro de Porto Alegre virou a rua onde a água encobriu. Ah a Praia de Belas que é o shopping chamado Praia de Belas porque ali há mais de cem anos era praia, virou e não dou tudo, não dou tudo. Então é indescritível, mas o que choca é o conjunto da avalanche, da tragédia, porque na verdade as chuvas fortes começaram na serra. Eu diria assim em média cento e cinquenta quilômetro de Porto Alegre, numa faixa de largura de cento e cinquenta quilômetro e de comprimento vindo da divisa com Santa Catarina até o centro do estado de Santa Maria, uma faixa de quatrocentos quilômetro. Então cento e cinquenta quilômetros de largura por quatrocentos de comprimento. Chuvas torrenciais na serra que foram baixando, trazendo tudo pra baixo, é uma coisa assim impressionante, com desmoronamento de morro, desmoronamento de morro, queda de barreira, pontes e os rios foram descendo e vieram pros vales. Aí o pior, o mais atingido vale do Taquari, o Vale do Caí, Vale do Taquari, Estrela Lajeado, aquela região ali, o Vale do Caí é São Sebastião do Caí, Montenegro, arrasado, o Vale do Paranhana, a cidade de Três Coroas, Igrejinha para o Beto, Araraquara, o Vale dos Sinos, São Leopoldo, Novo Hamburgo, São Leopoldo está debaixo d'água, ainda, o 0 vale do Rio Pardo, Santa Cruz, Candelaria, Vera Cruz, o Vale do Jacuí, mais abaixo, que é o grande rio que desagam a maioria dos de desses vales, o Vale do Jacuí em Cachoeira do Sul e tudo isso se juntou ainda ao Vale do do Gravataí, tudo isso desceu pra Porto Alegre, todos os rios desceram pra Porto Alegre. E aí a tragédia que Porto Alegre está enfrentando porque todas as águas chegaram no Guaíba e represaram. E o Guaíba que em mil novecentos e quarenta e tinha se levado a quatro metros e sessenta, quatro metros e setenta, foi pra cinco metro e meio. E aí uma coisa assim que difícil de acreditar, difícil de ver, mas vendo só vendo pra crer. Já temos contabilizado hoje noventa mortes, cento e trinta e dois desaparecidos que não se pode imaginar outra outra realidade, são as cidades de Canoas, Canoas uma cidade com trezentos, quatrocentos mil habitantes, dois terço embaixo da água. A cidade de Eldorado do Sul trinta mil habitantes sobrou sobrou nada. Tudo embaixo d'água. O prefeito Hernandi Gonçalves está na prefeitura no quarto andar da prefeitura há cinco, seis dias sem roupa, sem com a roupa do couro, sem nada. Guaíba não é diferente de uma realidade, o prefeito Marcelo Maranata, sofrendo muito lá, a cidade invadida, Alvorada pelo outro lado, Cachoeirinha, Gravataí, ou seja, a região metropolitana, ilhada, ninguém entra ninguém sai o que sai é pôr caos pra sair a Porto Alegre tem cinco saída agora tem meia porque é uma a menor saída que é por Viamão Então é uma é quadro assim de muita dor, de muito sofrimento, perdas humanas, sabe aquilo que tem valor e tem preço? O que tem valor não tem preço. Isso não tem preço. Mas tem patrimônios que não sei quando vão recuperar. Não sei como recuperar, é é inimaginável porque as pessoas desalojadas, cidades no Vale do Taquari, por exemplo, Cruzeiro do Sul, varreu, varreu, sobrou nada. Onde era bairro com quinhentas casas não sobrou uma. Acabaram as empresas, acabaram",
      "summary": " Deputado relata dor e devastação no Rio Grande do Sul: chuva forte causa inundação em Porto Alegre e vales vizinhos, resultando em mortes, desaparecidos e destruição de cidades. A metrópole sofre com quedas no nível do rio Guaíba e dificuldades de transporte. Perda de patrimônios é imensa e irrecuperável.",
      "speaker": {
        "id": 73486,
        "name": "Pompeo de Mattos",
        "position": "Deputado"
      }
    },
    {
      "start_time": 1715082910,
      "duration": 3,
      "transcription": "Tudo, acabou tudo, tudo tudo. Empresa",
      "speaker": {
        "id": 204441,
        "name": "Otoni de Paula",
        "position": "Deputado"
      }
    },
    {
      "start_time": 1715082913,
      "duration": 206,
      "transcription": "Meu Deus. Nós temos que, é é é rever o conceito, é quase rever conceito de vida. E eu estou narrando isso aqui com o coração cortado porque eu eu estava lá vivendo. Daí como reação é verdade o Governo Federal, presidente Lula esteve lá em Santa Maria, viu o tamanho da tragédia na parte central e depois com dimensão muito maior vem a veio a Porto Alegre e aí com a presença do presidente Lira muito importante a presença do presidente da Câmara dos Deputados, importante a presidência, a presença do presidente do senado Rodrigo Pacheco, do ministro vicepresidente do Supremo Tribunal Federal, ministro Fachin, presidente do Tribunal de Contas, quatorze ministros, os deputados federais todos ali, né, com os olhos marejados, como estou, deputados estaduais, o governador Eduardo Lei, prefeitos todos não não há não há disputa se é da direita, se é da esquerda, se é desse ou daquele partido, é tragédia, é tragédia, é o olhar pro ser humano, olhar pras vidas, olhar pras almas. É uma coisa assim que que choca, que choca muito. Então ah uma iniciativa nós viemos ontem não a aeroporto você foi no mínimo trinta dia o aeroporto nós não temos comunicação, por estrada, estava lá o ministro Renan, Renan Filho, que é acho que é do seu partido inclusive. Sim, sim. Muito, muito dedicado, colocou toda a a que é possível à disposição, mas não tem como sair de Porto Alegre, não tem como se comunicar com o interior, as estradas, a cento e noventa, a duzentos e noventa, a cento e dezesseis, na três oito meia, todos todas rodovias trancada com quedas de barreira, com cabeceira de ponte, é uma coisa assim chocante, impressionante o estádio do Grêmio invadido, futebol, cheio d'água. Estágio do Esporte Clube Internacional, todo cheio d'água. Não, é difícil de acreditar só vendo pra que contando as pessoa na medida, mas hoje tem imagem que as imagem podem podem mostrar o 0 que está acontecendo lá. Então assim nós viemos pra Brasília ontem com o avião da FAB, a FAB nos eu diria assim nos resgatou os deputados gaúcho pra virem aqui, votamos já ontem à noite, né? Uma medida, projeto de decreto legislativo dois três seis de dois mil e vinte e quatro que decreta estado de calamidade pública até trinta e de doze de Novo Rio Grande do Sul. O que que significa isso pra que as pessoas entendam? Significa dizer que com isso nós tiramos toda a burocracia pra que a gente possa efetivamente lançar mão de recursos que efetivamente deem respostas imediata, imediata, porque não tem luz, não tem água, eu moro no centro de Porto Alegre, não tem luz, tem água. No centro próximo ao palácio. Não tem luz, tem água. O centro de Porto Alegre nada, nada, 0. Tudo invadido pela água e tiver que desligar. Né e a água Porto Alegre não vai ter já já toda Porto Alegre não tem água é somente imaginar meu querido Pompeu",
      "summary": " Deputado relata tragédia em Santa Maria e Porto Alegre, falando em rever conceito de vida e união de partidos. Projeto de decreto legislativo aprovado para estado de calamidade pública no Rio Grande do Sul, visando retirar burocracia e fornecer recursos imediatos a região afetada, que sofre sem luz e água.",
      "speaker": {
        "id": 73486,
        "name": "Pompeo de Mattos",
        "position": "Deputado"
      }
    },
    {
      "start_time": 1715083119,
      "duration": 119,
      "transcription": "Que, nesse momento e quando nós falamos aqui enquanto parlamentares, nós falamos pro nosso Estado, pro nosso povo, e só de imaginar de que nesse momento o Brasil todo terá a oportunidade de ver a sua fala, de sentir a sua emoção, menos o Rio Grande, porque na verdade não há comunicação Não há, não há. Não há energia elétrica Não há. Ou seja, é estado hoje isolado do Brasil. Nós estamos saindo na quartafeira lá do Rio de Janeiro, em nome da nossa igreja, em nome da nossa convenção das Assembleias de Deus, ministério de Madureira, no Rio de Janeiro, com caminhão truncado com mais de mil cestas básicas e difícil é saber aonde vamos conseguir chegar, não é? E nós já traçamos já ali uma rota e vamos chegar lá em Ruben Berta, não é ali próximo ali. Rubens Berta. Isso e vamos ali deixar como ponto uma uma de nossas igrejas, mas eu quero que você saiba, meu querido e grande amigo e companheiro, de batalhas aqui no parlamento, de que o Brasil todo está em oração, de que o Brasil todo está orando, rezando os nossos irmãos católicos, todos estão clamando a Deus e aos céus para que a misericórdia divina recaia sobre este povo que está vivendo o 0 maior drama da história desta nação em termos de catástrofe natural, e a nossa solidariedade Pompeu, de verdade, de verdade. Pra mim concluí então, deputado",
      "summary": " Deputado informa: Estado do Rio Grande está isolado, falta energia elétrica e comunicação; viajando com ajuda humanitária para Rubens Berta; Brasil orando por misericórdia divina e solidariedade em face da catástrofe natural.",
      "speaker": {
        "id": 204441,
        "name": "Otoni de Paula",
        "position": "Deputado"
      }
    },
    {
      "start_time": 1715083238,
      "duration": 220,
      "transcription": "Paulo, obrigado pelo carinho, a sua solidariedade, a solidariedade do povo do Rio de Janeiro, do povo brasileiro, do governo brasileiro, agradecer a a os voluntário, é uma coisa assim, se por lado a gente vive a tragédia, por outro lado vê os corações humanos, a humanidade, o humanismo, o sentimento, as igreja, igrejas evangélicas, igreja católica, ou seja, os cristãos sofrendo junto e e agindo, reagindo, voluntários, expondo as suas vidas, né? De jet ski, de barco, bombeiros civis, militares, defesa civil. Olha, gratidão, gratidão, gratidão, gratidão Brasil, gratidão o povo gaúcho, aqueles que tão fazendo a diferença e nós tamo tentando fazer a nossa parte por outro lado pra levar os recursos exatamente de chegar, dar resposta e nós reconstruir o Rio Grande. O Rio Grande que ofereceu tantos homens e mulheres pro Brasil, tantos líderes para o Brasil e e ajudou tanto o Brasil, eu não tenho dúvida que o 0 Brasil já está ajudando o Rio Grande com a sua solidariedade, com a sua ação, com sua atitude, nós estamos sentindo isso, isso nos nos alimenta a fé, nos alimenta a esperança que Deus nos proteja, nos ilumine ah e e até porque promete vir mais chuva segundafeira. É verdade. Chuva e tempo frio. Mas Deus sabe o propósito que tem e e se ele dá tudo isso e haverá de nos dar a força suficiente pra que a gente possa pra que a gente possa superar tudo isso. Então eu quero terminando aqui agradecer, reitero terminando quando comecei, agradecer a Deus, Deus olhar pro Rio Grande, nos proteger, colocar a sua mão generosa em cima como uma capa de proteção pra que a gente possa sobreviver, ter dignidade. Olha, é sem palavras, são de quatrocentos e noventa e sete município, quatrocentos municípios em em estado de calamidade. Isso não tem, não tem precedente. Então, ah muito obrigado deputado Antônio de Paula pela generosidade de eu estar aqui na na comissão de educação, abrir esse espaço pra gente poder transmitir pro Brasil pro mundo dizendo o que que aconteceu lá e isso isso em três anos nós tínhamos três tragédia, mas nenhuma se aliás em ano três tragédia, especialmente do Vale do Taquari, mas nenhuma se iguala a essa, o que quer dizer que tem tem coisa diferente no ar, nós temos que aprender isso. Verdade. Tirar lições disso, Porque tem tem coisas errada, tem coisa errada. E nós temos que rever conceitos, rever comportamentos, rever normas, rever atitude, mas nessa hora nós temos que mais do que discutir o futuro é nós fazer o presente ou já, o imediato socorrer o nosso povo e a nossa agenda. É o que nós viemos fazer em Brasília, voltamos amanhã de noite e de novo pelo avião da FAB, Temos aqui exatamente pra ajustar esses documentos, essas autorizações, essas regras, essas leis, tá desburocratizar, mandar as verba, prestar o socorro que o Brasil está oferecendo, que o Rio Grande precisa e que nós queremos levar daqui pra lá se Deus quiser. Muito obrigado a todos aqueles que estão na luta no Rio Grande do Sul, cada uma das cidades, muito obrigado ao Brasil que reconhece e vai dar o que o Rio Grande precisa nessa hora merece. Eu diria tem direito, mas mais do que isso, precisa e precisa muito. Obrigado, doutor. Deputado",
      "summary": " Deputado agradece solidariedade e ajuda aos afetados no Rio Grande do Sul, pede por orações e ação imediata. Reconhece problemas que devem ser abordados e espera por apoio contínuo do Brasil.",
      "speaker": {
        "id": 73486,
        "name": "Pompeo de Mattos",
        "position": "Deputado"
      }
    },
    {
      "start_time": 1715083458,
      "duration": 29,
      "transcription": "De Matos eu eu acredito que nunca será demais, nós vamos fazer minuto de silêncio mais uma vez nesta casa, eu creio que já tenha sido feito em homenagem em memória aos brasileiros mortos nesta tragédia que toca a todos nós.",
      "summary": " Deputado propõe novamente um minuto de silêncio em homenagem a brasileiros falecidos na tragédia atingindo a todos nós.",
      "speaker": {
        "id": 204441,
        "name": "Otoni de Paula",
        "position": "Deputado"
      }
    },
    {
      "start_time": 1715083487,
      "duration": 42,
      "transcription": "Acreditando na",
      "speaker": {
        "name": "1 minuto de silêncio",
        "position": ""
      }
    },
    {
      "start_time": 1715083529,
      "duration": 31,
      "transcription": "Na misericórdia divina nos despedimos do Brasil e do povo do Rio Grande desejando que a paz de Deus que excede a todo o entendimento possa visitar esse estado nesse momento de dor e de dificuldade. Está encerrado esta audiência pública.",
      "summary": " Deputado pede por paz de Deus em Estado afligido, termina audiência pública.",
      "speaker": {
        "id": 204441,
        "name": "Otoni de Paula",
        "position": "Deputado"
      }
    }
  ],
  "updated_at": 1715937526
}